tap_exactonline/__init__.py
tap_exactonline/client.py
tap_exactonline/helpers/ExactApiWrapper.py
tap_exactonline/helpers/parser.py
tap_exactonline/helpers/secretsManager.py
tap_exactonline/streams.py
tap_exactonline/tap.py
tap_exactonline/tests/__init__.py
tap_exactonline/tests/test_core.py
tap_exactonline-0.2.24.dist-info/METADATA
tap_exactonline-0.2.24.dist-info/WHEEL
tap_exactonline-0.2.24.dist-info/entry_points.txt
tap_exactonline-0.2.24.dist-info/RECORD
