Metadata-Version: 2.1
Name: tap-exactonline
Version: 0.2.24
Summary: `tap-exactonline` is a Singer tap for ExactOnline, built with the Meltano SDK for Singer Taps.
License: Apache 2.0
Keywords: ELT,ExactOnline
Author: Hidde Stokvis
Requires-Python: >=3.7.1,<3.11
Classifier: License :: Other/Proprietary License
Classifier: Programming Language :: Python :: 3
Classifier: Programming Language :: Python :: 3.8
Classifier: Programming Language :: Python :: 3.9
Classifier: Programming Language :: Python :: 3.10
Requires-Dist: boto3 (>=1.24.79,<2.0.0)
Requires-Dist: exactonline (>=0.4.0,<0.5.0)
Requires-Dist: requests (>=2.25.1,<3.0.0)
Requires-Dist: singer-sdk (>=0.7.0,<0.8.0)
